{
  "schema": "skenion.node.definition",
  "schemaVersion": "0.1.0",
  "id": "audio.noise",
  "version": "0.1.0",
  "displayName": "Noise",
  "category": "Audio",
  "ports": [
    {
      "id": "seed",
      "direction": "input",
      "label": "Seed",
      "type": "control.message.any",
      "required": false,
      "messageSelectors": {
        "accepted": [
          "set",
          "float",
          "int",
          "uint"
        ],
        "silent": [
          "set"
        ],
        "store": [
          "set",
          "float",
          "int",
          "uint"
        ]
      }
    },
    {
      "id": "out",
      "direction": "output",
      "label": "Signal",
      "type": "signal.audio"
    }
  ],
  "execution": {
    "model": "audio_block",
    "clock": "audio"
  },
  "state": {
    "persistent": false
  },
  "permissions": [],
  "capabilities": [
    "pd.audio.v0.1"
  ],
  "surface": {
    "palette": "direct"
  }
}
