{
  "schema": "skenion.graph",
  "schemaVersion": "0.1.0",
  "id": "help-object-core-float",
  "revision": "1",
  "nodes": [
    {
      "id": "note_1",
      "params": {
        "text": "F32 stores a control payload. in emits, set stores silently, bang emits the current payload."
      },
      "ports": [],
      "implementation": {
        "provider": {
          "kind": "core"
        },
        "objectId": "comment"
      }
    },
    {
      "id": "bang_1",
      "params": {},
      "ports": [
        {
          "id": "in",
          "direction": "input",
          "label": "In",
          "type": "value.core.message",
          "required": false,
          "accepts": [
            "value.core.float64",
            "value.core.int64",
            "value.core.uint64",
            "value.core.bool",
            "value.core.bang"
          ],
          "messageKeys": {
            "accepted": [
              "bang",
              "float",
              "int",
              "uint",
              "bool"
            ],
            "trigger": [
              "bang",
              "float",
              "int",
              "uint",
              "bool"
            ],
            "emit": [
              "bang",
              "float",
              "int",
              "uint",
              "bool"
            ]
          }
        },
        {
          "id": "out",
          "direction": "output",
          "label": "Bang",
          "type": "value.core.bang"
        }
      ],
      "implementation": {
        "provider": {
          "kind": "core"
        },
        "objectId": "bang"
      }
    },
    {
      "id": "float_1",
      "params": {
        "value": 0.5,
        "representation": "f32"
      },
      "ports": [
        {
          "id": "in",
          "direction": "input",
          "label": "In",
          "type": "value.core.message",
          "required": false,
          "accepts": [
            "value.core.float64",
            "value.core.int64",
            "value.core.uint64",
            "value.core.bool",
            "value.core.bang"
          ],
          "messageKeys": {
            "accepted": [
              "bang",
              "set",
              "float",
              "int",
              "uint",
              "bool"
            ],
            "silent": [
              "set"
            ],
            "trigger": [
              "bang",
              "float",
              "int",
              "uint",
              "bool"
            ],
            "store": [
              "set",
              "float",
              "int",
              "uint",
              "bool"
            ],
            "emit": [
              "bang",
              "float",
              "int",
              "uint",
              "bool"
            ]
          }
        },
        {
          "id": "cold",
          "direction": "input",
          "label": "Cold",
          "type": "value.core.float64",
          "required": false
        },
        {
          "id": "value",
          "direction": "output",
          "label": "Value",
          "type": "value.core.float64"
        }
      ],
      "implementation": {
        "provider": {
          "kind": "core"
        },
        "objectId": "float"
      }
    },
    {
      "id": "target_1",
      "params": {},
      "ports": [
        {
          "id": "in",
          "direction": "input",
          "label": "In",
          "type": "value.core.message",
          "required": false,
          "messageKeys": {
            "accepted": [
              "bang",
              "set",
              "float",
              "int",
              "uint",
              "bool"
            ],
            "silent": [
              "set"
            ],
            "trigger": [
              "bang",
              "float",
              "int",
              "uint",
              "bool"
            ],
            "store": [
              "set",
              "float",
              "int",
              "uint",
              "bool"
            ],
            "emit": [
              "bang",
              "float",
              "int",
              "uint",
              "bool"
            ]
          }
        },
        {
          "id": "cold",
          "direction": "input",
          "label": "Cold",
          "type": "value.core.float64",
          "required": false
        },
        {
          "id": "value",
          "direction": "output",
          "label": "Value",
          "type": "value.core.float64"
        }
      ],
      "implementation": {
        "provider": {
          "kind": "core"
        },
        "objectId": "float"
      }
    }
  ],
  "edges": [
    {
      "id": "edge-1",
      "source": {
        "nodeId": "bang_1",
        "portId": "out"
      },
      "target": {
        "nodeId": "float_1",
        "portId": "in"
      }
    },
    {
      "id": "edge-2",
      "source": {
        "nodeId": "float_1",
        "portId": "value"
      },
      "target": {
        "nodeId": "target_1",
        "portId": "in"
      }
    }
  ]
}
